getbc.py
getbc-0.4.0.dist-info/LICENSE.txt
getbc-0.4.0.dist-info/METADATA
getbc-0.4.0.dist-info/WHEEL
getbc-0.4.0.dist-info/entry_points.txt
getbc-0.4.0.dist-info/top_level.txt
getbc-0.4.0.dist-info/RECORD
