Metadata-Version: 2.1
Name: getbc
Version: 0.4.0
Summary: Make installing bomcheckgui easy
Home-page: https://github.com/kcarlton55/getbc
Author: Kenneth Edward Carlton
Author-email: kencarlton55@gmail.com
License: GPLv3+
Keywords: bomcheckgui
Classifier: Programming Language :: Python :: 3
Classifier: Natural Language :: English
Classifier: License :: OSI Approved :: GNU General Public License v3 (GPLv3)
Classifier: Intended Audience :: Manufacturing
Classifier: Intended Audience :: End Users/Desktop
Classifier: Operating System :: OS Independent
Requires-Python: >=3.8
License-File: LICENSE.txt
